requests_session_plus/__init__.py
requests_session_plus-1.0.4.dist-info/LICENSE
requests_session_plus-1.0.4.dist-info/METADATA
requests_session_plus-1.0.4.dist-info/WHEEL
requests_session_plus-1.0.4.dist-info/top_level.txt
requests_session_plus-1.0.4.dist-info/RECORD
