Metadata-Version: 2.1
Name: requests-session-plus
Version: 1.0.4
Summary: Drop in replacement for requests.Session() with some QOL enhancements
Author-email: Hunter Chambers <chambersh1129@gmail.com>
License: GNU AFFERO GENERAL PUBLIC LICENSE
Project-URL: Homepage, https://github.com/chambersh1129/requests-session-plus
Keywords: requests,session,retry,timeout
Classifier: Programming Language :: Python
Classifier: Programming Language :: Python :: 3
Classifier: Development Status :: 5 - Production/Stable
Classifier: License :: OSI Approved :: GNU Affero General Public License v3
Classifier: Natural Language :: English
Requires-Python: >=3.7
License-File: LICENSE
Requires-Dist: requests
